{
  "project_info": {
    "project_number": "949976136000",
    "firebase_url": "https://namastey-6d119.firebaseio.com",
    "project_id": "namastey-6d119",
    "storage_bucket": "namastey-6d119.appspot.com"
  },
  "client": [
    {
      "client_info": {
        "mobilesdk_app_id": "1:949976136000:android:02f74fb8ba16c4f2f7e2a5",
        "android_client_info": {
          "package_name": "com.namastey"
        }
      },
      "oauth_client": [
        {
          "client_id": "949976136000-6d3449rm81adlvh516kt4mlc6c7iv5ks.apps.googleusercontent.com",
          "client_type": 1,
          "android_info": {
            "package_name": "com.namastey",
            "certificate_hash": "deeb765df890d8562e547f898f41f4d764139cb0"
          }
        },
        {
          "client_id": "949976136000-b2dkpit3tr38fq19jf6og5mj6ar5fcml.apps.googleusercontent.com",
          "client_type": 1,
          "android_info": {
            "package_name": "com.namastey",
            "certificate_hash": "928ab0c95f043abf365d75d10fea089a61f88b07"
          }
        },
        {
          "client_id": "949976136000-jb143m5g9se5g8thej91bci33t8n2si6.apps.googleusercontent.com",
          "client_type": 1,
          "android_info": {
            "package_name": "com.namastey",
            "certificate_hash": "7a95b288aba7982bf94c092ef930becb74bbb9e0"
          }
        },
        {
          "client_id": "949976136000-laf7dg2ugtf93thepqbf9ql7io914l1t.apps.googleusercontent.com",
          "client_type": 1,
          "android_info": {
            "package_name": "com.namastey",
            "certificate_hash": "d51dfe42bb7a652c5adcc152807f21a564558588"
          }
        },
        {
          "client_id": "949976136000-les45oc48t4bc2l37tsc6kuc4bi8rku5.apps.googleusercontent.com",
          "client_type": 1,
          "android_info": {
            "package_name": "com.namastey",
            "certificate_hash": "6e996c7658a8d4b88272727436fbfcf2c43ab045"
          }
        },
        {
          "client_id": "949976136000-t5au1bh7d839ekip3saahh4j4kmb3jnp.apps.googleusercontent.com",
          "client_type": 1,
          "android_info": {
            "package_name": "com.namastey",
            "certificate_hash": "35f4f15ff193d3745c7dd2801b363c9256229c82"
          }
        },
        {
          "client_id": "949976136000-ddq2cdt6do3d2vguu093l7t5j8570rd9.apps.googleusercontent.com",
          "client_type": 3
        }
      ],
      "api_key": [
        {
          "current_key": "AIzaSyCj4_1sbJh-ETKXz6owFeRf0x86j2J9Uac"
        }
      ],
      "services": {
        "appinvite_service": {
          "other_platform_oauth_client": [
            {
              "client_id": "949976136000-ddq2cdt6do3d2vguu093l7t5j8570rd9.apps.googleusercontent.com",
              "client_type": 3
            },
            {
              "client_id": "949976136000-8hh1qt6rnmspf0oeaqqqea49lj7jb5sg.apps.googleusercontent.com",
              "client_type": 2,
              "ios_info": {
                "bundle_id": "com.namastey.ios",
                "app_store_id": "1507928881"
              }
            }
          ]
        }
      }
    }
  ],
  "configuration_version": "1"
}